lavender_harmonious_society/__init__.py
lavender_harmonious_society/XJP/__init__.py
lavender_harmonious_society/XJP/name_taboo.py
lavender_harmonious_society-0.0.7.dist-info/licenses/LICENSE
lavender_harmonious_society-0.0.7.dist-info/METADATA
lavender_harmonious_society-0.0.7.dist-info/WHEEL
lavender_harmonious_society-0.0.7.dist-info/top_level.txt
lavender_harmonious_society-0.0.7.dist-info/RECORD
