Metadata-Version: 2.4
Name: Lavender-Harmonious-Society
Version: 0.0.7
Summary: A pip package for bypassing sensitive words.
Home-page: https://github.com/Zeyu-Xie/Lavender-Harmonious-Socirty
Author: Zeyu Xie
Author-email: xie.zeyu20@gmail.com
Classifier: Programming Language :: Python :: 3
Classifier: License :: OSI Approved :: GNU General Public License v3 (GPLv3)
Classifier: Operating System :: OS Independent
Requires-Python: >=3.6
License-File: LICENSE
Requires-Dist: myosotis_chinese_dictionary>=0.0.7
Dynamic: author
Dynamic: author-email
Dynamic: classifier
Dynamic: description
Dynamic: description-content-type
Dynamic: home-page
Dynamic: license-file
Dynamic: requires-dist
Dynamic: requires-python
Dynamic: summary
